whl_logmap/__init__.py
whl_logmap/add_signal.py
whl_logmap/extract_path.py
whl_logmap/funcs.py
whl_logmap/main.py
whl_logmap/map_gen.py
whl_logmap/plots.py
whl_logmap/preprocess.py
whl_logmap/utils.py
whl_logmap-0.0.10.dist-info/licenses/LICENSE
whl_logmap-0.0.10.dist-info/METADATA
whl_logmap-0.0.10.dist-info/WHEEL
whl_logmap-0.0.10.dist-info/entry_points.txt
whl_logmap-0.0.10.dist-info/top_level.txt
whl_logmap-0.0.10.dist-info/RECORD
