Metadata-Version: 2.4
Name: whl-logmap
Version: 0.0.10
Summary: wheelos map tool
Author-email: daohu527 <daohu527@gmail.com>
Project-URL: Homepage, https://github.com/wheelos-tools/whl-logmap
Project-URL: Bug Tracker, https://github.com/wheelos-tools/whl-logmap/issues
Keywords: logmap,wheelos,gis,mapping
Classifier: Programming Language :: Python :: 3
Classifier: Operating System :: OS Independent
Classifier: Intended Audience :: Developers
Classifier: Topic :: Scientific/Engineering :: GIS
Classifier: Programming Language :: Python :: 3 :: Only
Requires-Python: >=3.6
License-File: LICENSE
Requires-Dist: cyber_record
Requires-Dist: record_msg
Requires-Dist: shapely
Requires-Dist: matplotlib
Requires-Dist: scipy
Dynamic: license-file
